trioyoyo
