Metadata-Version: 1.1
Name: trioyoyo
Version: 1.1.23
Summary: A trio oyoyo port
Home-page: https://github.com/henry232323/trioyoyo
Author: henry232323
Author-email: henry@typheus.me
License: GPL
Keywords: IRC Trio Async
Platform: UNKNOWN
Classifier: Development Status :: 5 - Production/Stable
Classifier: Intended Audience :: Developers
Classifier: Topic :: Communications :: Chat :: Internet Relay Chat
Classifier: License :: OSI Approved :: MIT License
Classifier: Programming Language :: Python :: 3.5
Classifier: Programming Language :: Python :: 3.6
